proface/preprocessor/__init__.py
proface/preprocessor/__main__.py
proface/preprocessor/_version.py
proface/preprocessor/cli.py
proface/preprocessor/py.typed
proface_pre-0.2.2.dist-info/METADATA
proface_pre-0.2.2.dist-info/WHEEL
proface_pre-0.2.2.dist-info/entry_points.txt
proface_pre-0.2.2.dist-info/RECORD
